ipc_client/__init__.py
ipc_client/ipc_client.py
ipc_client-0.0.1.dist-info/METADATA
ipc_client-0.0.1.dist-info/WHEEL
ipc_client-0.0.1.dist-info/licenses/LICENSE
ipc_client-0.0.1.dist-info/RECORD
